floria_strainer/__init__.py
floria_strainer/cli.py
floria_strainer/main.py
floria_strainer/parser.py
floria_strainer-0.2.1.dist-info/LICENSE
floria_strainer-0.2.1.dist-info/METADATA
floria_strainer-0.2.1.dist-info/WHEEL
floria_strainer-0.2.1.dist-info/entry_points.txt
floria_strainer-0.2.1.dist-info/RECORD
