Metadata-Version: 2.1
Name: floria-strainer
Version: 0.2.1
Summary: 
Author: maxibor
Author-email: maxime.borry@gmail.com
Requires-Python: >=3.10,<4.0
Classifier: Programming Language :: Python :: 3
Classifier: Programming Language :: Python :: 3.10
Classifier: Programming Language :: Python :: 3.11
Classifier: Programming Language :: Python :: 3.12
Requires-Dist: click (>=8.1.7,<9.0.0)
Requires-Dist: numpy (>=1.26.4,<2.0.0)
Requires-Dist: pandas (>=2.2.1,<3.0.0)
Requires-Dist: pysam (>=0.22.0,<0.23.0)
Requires-Dist: rich-click (>=1.7.4,<2.0.0)
Requires-Dist: scikit-learn (>=1.4.1.post1,<2.0.0)
